smtp_tlsa_verify/__init__.py
smtp_tlsa_verify/__main__.py
smtp_tlsa_verify/api.py
smtp_tlsa_verify/cli.py
smtp_tlsa_verify/dns_records.py
smtp_tlsa_verify/verification.py
smtp_tlsa_verify-0.1.1.dist-info/METADATA
smtp_tlsa_verify-0.1.1.dist-info/WHEEL
smtp_tlsa_verify-0.1.1.dist-info/entry_points.txt
smtp_tlsa_verify-0.1.1.dist-info/licenses/LICENSE.txt
smtp_tlsa_verify-0.1.1.dist-info/RECORD
