Metadata-Version: 2.4
Name: smtp-tlsa-verify
Version: 0.1.1
Summary: A small library, command-line utility and JSON/HTTP/FastAPI service to check DANE/TLSA-RRs against SMTP servers.
License-File: LICENSE.txt
Classifier: License :: OSI Approved :: GNU Affero General Public License v3
Requires-Python: >=3.11
Requires-Dist: dnspython>=2.7.0
Requires-Dist: fastapi[standard]>=0.116.1
Requires-Dist: pydantic>=2.11.7
Provides-Extra: fastapi
Requires-Dist: fastapi[standard]>=0.116.1; extra == 'fastapi'
